kof_parser/KoordSys.csv
kof_parser/__init__.py
kof_parser/enums.py
kof_parser/exceptions.py
kof_parser/kof.py
kof_parser/model.py
kof_parser/parser.py
kof_parser/writer.py
kof_parser-0.1.4.dist-info/METADATA
kof_parser-0.1.4.dist-info/WHEEL
kof_parser-0.1.4.dist-info/licenses/LICENSE
kof_parser-0.1.4.dist-info/RECORD
