Metadata-Version: 2.4
Name: kof-parser
Version: 0.1.4
Summary: A KOF file parser. Follows Norkart's KOF 2.0 specification from 2005.
Project-URL: Homepage, https://github.com/norwegian-geotechnical-institute/kof-parser
Project-URL: Repository, https://github.com/norwegian-geotechnical-institute/kof-parser
Author-email: Magnus Mariero <magnus@neate.no>, Jostein Leira <jostein@leira.net>
Maintainer-email: Jostein Leira <jostein@leira.net>
License: MIT
License-File: LICENSE
Classifier: Development Status :: 5 - Production/Stable
Classifier: Operating System :: OS Independent
Classifier: Topic :: Scientific/Engineering :: GIS
Requires-Python: <4,>=3.11
Requires-Dist: charset-normalizer
Requires-Dist: coordinate-projector
Requires-Dist: pydantic<3,>=2.11
